pywrangler/__init__.py
pywrangler/__main__.py
pywrangler/cli.py
pywrangler/metadata.py
pywrangler/py.typed
pywrangler/sync.py
pywrangler/types.py
pywrangler/utils.py
workers_py-1.6.2.dist-info/METADATA
workers_py-1.6.2.dist-info/WHEEL
workers_py-1.6.2.dist-info/entry_points.txt
workers_py-1.6.2.dist-info/RECORD
