Metadata-Version: 2.4
Name: workers-py
Version: 1.6.2
Summary: A set of libraries and tools for Python Workers
Project-URL: Homepage, https://github.com/cloudflare/workers-py
Project-URL: Bug Tracker, https://github.com/cloudflare/workers-py/issues
Classifier: License :: OSI Approved :: MIT License
Classifier: Operating System :: OS Independent
Classifier: Programming Language :: Python :: 3
Requires-Python: >=3.12
Requires-Dist: click<9.0.0,>=8.0.0
Requires-Dist: pyjson5>=1.6.0
Requires-Dist: pyodide-cli
Requires-Dist: pyodide-py
Requires-Dist: rich>=13.0.0
Requires-Dist: workers-runtime-sdk>=0.1.0
Provides-Extra: build
Requires-Dist: uv~=0.5.23; extra == 'build'
